bank_sysiaia/__init__.py
bank_sysiaia/bank.py
bankssysia-0.0.1.dist-info/METADATA
bankssysia-0.0.1.dist-info/WHEEL
bankssysia-0.0.1.dist-info/top_level.txt
bankssysia-0.0.1.dist-info/RECORD
