Metadata-Version: 2.1
Name: bankssysia
Version: 0.0.1
Summary: bank account
Author: m
Author-email: 
Requires-Python: >=3.8
